alibabacloud_servicecatalog20210901/__init__.py
alibabacloud_servicecatalog20210901/client.py
alibabacloud_servicecatalog20210901/models/__init__.py
alibabacloud_servicecatalog20210901/models/_approve_provisioned_product_plan_request.py
alibabacloud_servicecatalog20210901/models/_approve_provisioned_product_plan_response.py
alibabacloud_servicecatalog20210901/models/_approve_provisioned_product_plan_response_body.py
alibabacloud_servicecatalog20210901/models/_associate_principal_with_portfolio_request.py
alibabacloud_servicecatalog20210901/models/_associate_principal_with_portfolio_response.py
alibabacloud_servicecatalog20210901/models/_associate_principal_with_portfolio_response_body.py
alibabacloud_servicecatalog20210901/models/_associate_product_with_portfolio_request.py
alibabacloud_servicecatalog20210901/models/_associate_product_with_portfolio_response.py
alibabacloud_servicecatalog20210901/models/_associate_product_with_portfolio_response_body.py
alibabacloud_servicecatalog20210901/models/_associate_tag_option_with_resource_request.py
alibabacloud_servicecatalog20210901/models/_associate_tag_option_with_resource_response.py
alibabacloud_servicecatalog20210901/models/_associate_tag_option_with_resource_response_body.py
alibabacloud_servicecatalog20210901/models/_cancel_provisioned_product_plan_request.py
alibabacloud_servicecatalog20210901/models/_cancel_provisioned_product_plan_response.py
alibabacloud_servicecatalog20210901/models/_cancel_provisioned_product_plan_response_body.py
alibabacloud_servicecatalog20210901/models/_copy_product_request.py
alibabacloud_servicecatalog20210901/models/_copy_product_response.py
alibabacloud_servicecatalog20210901/models/_copy_product_response_body.py
alibabacloud_servicecatalog20210901/models/_create_constraint_request.py
alibabacloud_servicecatalog20210901/models/_create_constraint_response.py
alibabacloud_servicecatalog20210901/models/_create_constraint_response_body.py
alibabacloud_servicecatalog20210901-1.2.3.dist-info/LICENSE
alibabacloud_servicecatalog20210901-1.2.3.dist-info/METADATA
alibabacloud_servicecatalog20210901-1.2.3.dist-info/WHEEL
alibabacloud_servicecatalog20210901-1.2.3.dist-info/top_level.txt
alibabacloud_servicecatalog20210901-1.2.3.dist-info/RECORD
